README.md
setup.py
big_todo.egg-info/PKG-INFO
big_todo.egg-info/SOURCES.txt
big_todo.egg-info/dependency_links.txt
big_todo.egg-info/entry_points.txt
big_todo.egg-info/requires.txt
big_todo.egg-info/top_level.txt
btodo/__init__.py