Metadata-Version: 2.1
Name: big-todo
Version: 0.0.5
Summary: CLI tool to combine TODO files
Home-page: https://github.com/jakekara/big-todo
Author: Jake Kara
Author-email: jake@jakekara.com
License: UNKNOWN
Platform: UNKNOWN
Classifier: Programming Language :: Python :: 3
Classifier: License :: OSI Approved :: MIT License
Classifier: Operating System :: OS Independent
Requires-Python: >=3.6
